[
    {
        "id" : 1,
        "name" : "Tutorial de JS",
        "image" : "aside-01.jpg",
        "message" : "10% OFF"
    },
    {
        "id" : 2,
        "name" : "Tutorial de NodeJS",
        "image" : "aside-02.jpg",
        "message" : "30% OFF"
    },
    {
        "id" : 3,
        "name" : "Tutorial de Express",
        "image" : "aside-03.jpg",
        "message" : "20% OFF"
    },
    {
        "id" : 4,
        "name" : "Tutorial de JSON",
        "image" : "aside-04.jpg",
        "message" : "50% OFF"
    }
]